{
    "os": "Linux-5.15.0-92-generic-x86_64-with-glibc2.29",
    "python": "3.8.10",
    "heartbeatAt": "2024-02-06T10:52:51.081787",
    "startedAt": "2024-02-06T10:52:49.806077",
    "docker": null,
    "cuda": null,
    "args": [],
    "state": "running",
    "program": "train.py",
    "codePathLocal": "train.py",
    "codePath": "train.py",
    "host": "nash-m5",
    "username": "muneeb",
    "executable": "/home/muneeb/Desktop/zuha/.env/bin/python",
    "cpu_count": 24,
    "cpu_count_logical": 32,
    "cpu_freq": {
        "current": 3391.4458125,
        "min": 800.0,
        "max": 4937.5
    },
    "cpu_freq_per_core": [
        {
            "current": 3000.0,
            "min": 800.0,
            "max": 5500.0
        },
        {
            "current": 3000.0,
            "min": 800.0,
            "max": 5500.0
        },
        {
            "current": 5462.338,
            "min": 800.0,
            "max": 5500.0
        },
        {
            "current": 3000.0,
            "min": 800.0,
            "max": 5500.0
        },
        {
            "current": 5477.058,
            "min": 800.0,
            "max": 5800.0
        },
        {
            "current": 3000.0,
            "min": 800.0,
            "max": 5800.0
        },
        {
            "current": 3000.0,
            "min": 800.0,
            "max": 5800.0
        },
        {
            "current": 3000.0,
            "min": 800.0,
            "max": 5800.0
        },
        {
            "current": 5482.768,
            "min": 800.0,
            "max": 5500.0
        },
        {
            "current": 3000.0,
            "min": 800.0,
            "max": 5500.0
        },
        {
            "current": 3000.0,
            "min": 800.0,
            "max": 5500.0
        },
        {
            "current": 3000.0,
            "min": 800.0,
            "max": 5500.0
        },
        {
            "current": 3000.0,
            "min": 800.0,
            "max": 5500.0
        },
        {
            "current": 3000.0,
            "min": 800.0,
            "max": 5500.0
        },
        {
            "current": 3000.0,
            "min": 800.0,
            "max": 5500.0
        },
        {
            "current": 3000.0,
            "min": 800.0,
            "max": 5500.0
        },
        {
            "current": 3000.0,
            "min": 800.0,
            "max": 4300.0
        },
        {
            "current": 4300.001,
            "min": 800.0,
            "max": 4300.0
        },
        {
            "current": 3000.0,
            "min": 800.0,
            "max": 4300.0
        },
        {
            "current": 3000.0,
            "min": 800.0,
            "max": 4300.0
        },
        {
            "current": 3000.0,
            "min": 800.0,
            "max": 4300.0
        },
        {
            "current": 4297.154,
            "min": 800.0,
            "max": 4300.0
        },
        {
            "current": 3000.0,
            "min": 800.0,
            "max": 4300.0
        },
        {
            "current": 4300.232,
            "min": 800.0,
            "max": 4300.0
        },
        {
            "current": 3000.0,
            "min": 800.0,
            "max": 4300.0
        },
        {
            "current": 3000.0,
            "min": 800.0,
            "max": 4300.0
        },
        {
            "current": 3000.0,
            "min": 800.0,
            "max": 4300.0
        },
        {
            "current": 3000.0,
            "min": 800.0,
            "max": 4300.0
        },
        {
            "current": 3000.0,
            "min": 800.0,
            "max": 4300.0
        },
        {
            "current": 3000.0,
            "min": 800.0,
            "max": 4300.0
        },
        {
            "current": 3000.0,
            "min": 800.0,
            "max": 4300.0
        },
        {
            "current": 3000.0,
            "min": 800.0,
            "max": 4300.0
        }
    ],
    "disk": {
        "/": {
            "total": 1824.7165718078613,
            "used": 1721.9231796264648
        }
    },
    "gpu": "NVIDIA GeForce RTX 3090",
    "gpu_count": 2,
    "gpu_devices": [
        {
            "name": "NVIDIA GeForce RTX 3090",
            "memory_total": 25769803776
        },
        {
            "name": "NVIDIA GeForce RTX 3090 Ti",
            "memory_total": 25757220864
        }
    ],
    "memory": {
        "total": 62.60425567626953
    }
}
